cmd_fanyi-0.0.4.data/scripts/fanyi
cmd_fanyi-0.0.4.dist-info/DESCRIPTION.rst
cmd_fanyi-0.0.4.dist-info/METADATA
cmd_fanyi-0.0.4.dist-info/RECORD
cmd_fanyi-0.0.4.dist-info/WHEEL
cmd_fanyi-0.0.4.dist-info/metadata.json
cmd_fanyi-0.0.4.dist-info/top_level.txt
translate/__init__.py
translate/baidu.py
translate/bing.py
translate/cache.py
translate/factory.py
translate/translator.py
translate/youdao.py
translate/util/__init__.py
translate/util/baidu_response_format.py
translate/util/baidu_sign.py
translate/util/formatBuilder.py
translate/util/lang.py
xml2dict/__init__.py
xml2dict/xml2dict.py
